apnggif.py
apnggif_sys.cp37-win_amd64.pyd
apnggif-0.1.4.dist-info/METADATA
apnggif-0.1.4.dist-info/WHEEL
apnggif-0.1.4.dist-info/entry_points.txt
apnggif-0.1.4.dist-info/top_level.txt
apnggif-0.1.4.dist-info/RECORD
