Metadata-Version: 2.1
Name: apnggif
Version: 0.1.4
Summary: Python interface to apng2gif
Home-page: https://github.com/yukinarit/apnggif
Author: yukinarit
Author-email: yukinarit84@gmail.com
License: zlib/libpng
Platform: UNKNOWN
Classifier: Development Status :: 4 - Beta
Classifier: Environment :: Console
Classifier: Intended Audience :: Developers
Classifier: License :: OSI Approved :: zlib/libpng License
Classifier: Programming Language :: Python :: 3.6
Classifier: Programming Language :: Python :: 3.7
Classifier: Programming Language :: Python :: 3.8
Classifier: Programming Language :: Python :: 3.9
Classifier: Programming Language :: Python :: 3.10
Classifier: Programming Language :: Python :: Implementation :: CPython
Classifier: Topic :: Scientific/Engineering :: Image Processing
Requires-Python: >=3.6
Requires-Dist: click
Requires-Dist: coloredlogs
